README.md
setup.py
CC_Adsorber.egg-info/PKG-INFO
CC_Adsorber.egg-info/SOURCES.txt
CC_Adsorber.egg-info/dependency_links.txt
CC_Adsorber.egg-info/requires.txt
CC_Adsorber.egg-info/top_level.txt
adsorber/__init__.py
adsorber/adsorb.py
adsorber/emt.py
adsorber/filter_functions.py
adsorber/surface_builder.py
adsorber/utilities.py
adsorber/gui/__init__.py
adsorber/gui/gui.py
adsorber/gui/layout.py
adsorber/objects/__init__.py
adsorber/objects/adsorbate.py
adsorber/objects/asv.py
adsorber/objects/site.py