Metadata-Version: 1.2
Name: CC-Adsorber
Version: 0.1.1
Summary: Tools for computational catalyst research
Home-page: https://github.com/statt8900/Adsorber
Author: Michael Statt
Author-email: mstatt@stanford.edu, ksb@stanford.edu
License: APACHE LICENSE, VERSION 2.0
Platform: UNKNOWN
Classifier: Development Status :: 4 - Beta
Classifier: Intended Audience :: Developers
Classifier: Topic :: Scientific/Engineering :: Chemistry
Classifier: Programming Language :: Python :: 3.6
Requires-Python: >3.6, <4
